ust_download_cache/__init__.py
ust_download_cache/cached_file.py
ust_download_cache/errors.py
ust_download_cache/ust_download_cache.py
UST_Download_Cache-2.1.0.dist-info/LICENSE
UST_Download_Cache-2.1.0.dist-info/METADATA
UST_Download_Cache-2.1.0.dist-info/WHEEL
UST_Download_Cache-2.1.0.dist-info/top_level.txt
UST_Download_Cache-2.1.0.dist-info/RECORD
