Metadata-Version: 2.1
Name: UST-Download-Cache
Version: 2.1.0
Summary: A package for caching downloads of specially formatted files.
Home-page: https://github.com/canonical/ust-download-cache
Author: Mike Salvatore <mike.salvatore@canonical.com>
License: UNKNOWN
Platform: UNKNOWN
Classifier: Programming Language :: Python :: 3
Classifier: License :: OSI Approved :: GNU General Public License v3 (GPLv3)
Classifier: Operating System :: POSIX :: Linux
Classifier: Topic :: Security
Requires-Python: >=3.5
Requires-Dist: requests
